setup.py
pyShift/Rmatrix.py
pyShift/__init__.py
pyShift/display.py
pyShift/motion.py
pyShift.egg-info/PKG-INFO
pyShift.egg-info/SOURCES.txt
pyShift.egg-info/dependency_links.txt
pyShift.egg-info/requires.txt
pyShift.egg-info/top_level.txt
pyShift/src/gengrid.c
pyShift/src/gengrid_stub.pyx
pyShift/test/__init__.py
pyShift/test/test_meshes.py
pyShift/test/test_motion.py