Metadata-Version: 1.0
Name: pyShift
Version: 0.1
Summary: Rigid Motion for 2D grids
Home-page: UNKNOWN
Author: ONERA/DSNA/CS2A Marc Poinot
Author-email: marc.poinot@onera.fr
License: UNKNOWN
Platform: UNKNOWN
